pacote_ajuda_mhr-0.0.4.dist-info/licenses/LICENSE
primeiro_pacote_mz/__init__.py
primeiro_pacote_mz/core.py
pacote_ajuda_mhr-0.0.4.dist-info/METADATA
pacote_ajuda_mhr-0.0.4.dist-info/WHEEL
pacote_ajuda_mhr-0.0.4.dist-info/top_level.txt
pacote_ajuda_mhr-0.0.4.dist-info/RECORD
