Metadata-Version: 2.4
Name: pacote-ajuda-mhr
Version: 0.0.4
Summary: Exemplo de biblioteca.
Author-email: Mateus <mateus.hrosa09@gmail.com>
License: MIT License
Requires-Python: >=3.9
License-File: LICENSE
Requires-Dist: requests>=2.31
Dynamic: license-file
